dcovlib/__init__.py
dcovlib/excel.py
dcovlib/ird.py
dcovlib-1.2.0.dist-info/METADATA
dcovlib-1.2.0.dist-info/WHEEL
dcovlib-1.2.0.dist-info/top_level.txt
dcovlib-1.2.0.dist-info/RECORD
