Metadata-Version: 2.1
Name: dcovlib
Version: 1.2.0
Summary: convert numpy to ird file, or convert ird to numpy    V1.1.0 add Excel
Home-page: https://github.com/SheepBreedingLab-HZAU/dcovlib
Author: Sun ling
Author-email: ling.sun-01@qq.com
Platform: Independant
Classifier: Programming Language :: Python :: 3
Classifier: License :: OSI Approved :: MIT License
Classifier: Operating System :: OS Independent
Requires-Python: >=3.6
Requires-Dist: numpy
Requires-Dist: pandas
